ncalab/__init__.py
ncalab/autostepper.py
ncalab/losses.py
ncalab/paths.py
ncalab/prediction.py
ncalab/utils.py
ncalab-0.3.1.dist-info/licenses/LICENSE
ncalab-0.3.1.dist-info/METADATA
ncalab-0.3.1.dist-info/WHEEL
ncalab-0.3.1.dist-info/top_level.txt
ncalab-0.3.1.dist-info/RECORD
